with_timeout.py
with_timeout-0.0.5.dist-info/LICENSE
with_timeout-0.0.5.dist-info/METADATA
with_timeout-0.0.5.dist-info/WHEEL
with_timeout-0.0.5.dist-info/top_level.txt
with_timeout-0.0.5.dist-info/RECORD
