Metadata-Version: 2.1
Name: with-timeout
Version: 0.0.5
Summary: 模拟requests的timeout参数，使任意函数都拥有超时跳出的功能，防止访问超时阻塞影响代码的运行
Home-page: https://github.com/snjyor/with_timeout
Author: snjyor
Author-email: snjyor@163.com
License: MIT
License-File: LICENSE
Requires-Dist: beautifulsoup4
